PackageManager/__main__.py
PackageManager/config_file.py
PackageManager/main.py
PPManager-0.3.1.dist-info/LICENSE
PPManager-0.3.1.dist-info/METADATA
PPManager-0.3.1.dist-info/WHEEL
PPManager-0.3.1.dist-info/entry_points.txt
PPManager-0.3.1.dist-info/top_level.txt
PPManager-0.3.1.dist-info/RECORD
