Metadata-Version: 2.1
Name: PPManager
Version: 0.3.1
Requires-Python: >=3.12
License-File: LICENSE
Requires-Dist: tomli-w==1.1.0
Requires-Dist: virtualenv==20.28.0
Requires-Dist: distlib==0.3.9
Requires-Dist: filelock==3.16.1
Requires-Dist: platformdirs==4.3.6
